PyAndroidTouch-0.1.0.data/data/pyandroidtouch/libs/arm64-v8a/android_touch
PyAndroidTouch-0.1.0.data/data/pyandroidtouch/libs/armeabi/android_touch
PyAndroidTouch-0.1.0.data/data/pyandroidtouch/libs/armeabi-v7a/android_touch
PyAndroidTouch-0.1.0.data/data/pyandroidtouch/libs/mips/android_touch
PyAndroidTouch-0.1.0.data/data/pyandroidtouch/libs/mips64/android_touch
PyAndroidTouch-0.1.0.data/data/pyandroidtouch/libs/x86/android_touch
PyAndroidTouch-0.1.0.data/data/pyandroidtouch/libs/x86_64/android_touch
pyandroidtouch/__init__.py
pyandroidtouch/adb.py
pyandroidtouch/base.py
pyandroidtouch/common.py
pyandroidtouch/py.py
pyandroidtouch/demo/__init__.py
pyandroidtouch/libs/arm64-v8a/android_touch
pyandroidtouch/libs/armeabi/android_touch
pyandroidtouch/libs/armeabi-v7a/android_touch
pyandroidtouch/libs/mips/android_touch
pyandroidtouch/libs/mips64/android_touch
pyandroidtouch/libs/x86/android_touch
pyandroidtouch/libs/x86_64/android_touch
pyandroidtouch/utils/__init__.py
pyandroidtouch/utils/math.py
PyAndroidTouch-0.1.0.dist-info/LICENSE
PyAndroidTouch-0.1.0.dist-info/METADATA
PyAndroidTouch-0.1.0.dist-info/WHEEL
PyAndroidTouch-0.1.0.dist-info/top_level.txt
PyAndroidTouch-0.1.0.dist-info/RECORD
