Metadata-Version: 2.1
Name: PyAndroidTouch
Version: 0.1.0
Summary: Python3 Android Touch Module, Base On "BobbleKeyboard/android_touch". Support Multi-Finger Tap/Swipe/Circle/Expand Action...
Home-page: https://github.com/HsOjo/PyAndroidTouch/
Author: HsOjo
Author-email: hsojo@qq.com
License: UNKNOWN
Keywords: hsojo python3 android ojopyadb touch
Platform: UNKNOWN
Classifier: Programming Language :: Python :: 3
Classifier: License :: OSI Approved :: MIT License
Classifier: Operating System :: OS Independent
Requires-Python: >=3.6
Requires-Dist: OjoPyADB (>=0.2.0)
